parallelencode/__init__.py
parallelencode/args.py
parallelencode/callbacks.py
parallelencode/run.py
parallelencode/VMAF/__init__.py
parallelencode/VMAF/target_vmaf.py
parallelencode/VMAF/vmaf.py
parallelencode/chunks/__init__.py
parallelencode/chunks/chunk.py
parallelencode/chunks/chunk_queue.py
parallelencode/chunks/resume.py
parallelencode/chunks/split.py
parallelencode/core/__init__.py
parallelencode/core/commandtypes.py
parallelencode/core/concat.py
parallelencode/core/encode.py
parallelencode/core/ffmpeg.py
parallelencode/core/fp_reuse.py
parallelencode/core/run_cmd.py
parallelencode/core/setup.py
parallelencode/core/utils.py
parallelencode/core/vapoursynth.py
parallelencode/encoders/__init__.py
parallelencode/encoders/aom.py
parallelencode/encoders/encoder.py
parallelencode/encoders/rav1e.py
parallelencode/encoders/svtav1.py
parallelencode/encoders/svtvp9.py
parallelencode/encoders/vpx.py
parallelencode/encoders/vvc.py
parallelencode/encoders/x264.py
parallelencode/encoders/x265.py
parallelencode/scenedetection/__init__.py
parallelencode/scenedetection/aom_kf.py
parallelencode/scenedetection/ffmpeg.py
parallelencode/scenedetection/pyscene.py
parallelencode/scenedetection/time.py
parallelencode-0.1.12.dist-info/LICENSE.md
parallelencode-0.1.12.dist-info/METADATA
parallelencode-0.1.12.dist-info/WHEEL
parallelencode-0.1.12.dist-info/top_level.txt
parallelencode-0.1.12.dist-info/RECORD
