Metadata-Version: 2.1
Name: parallelencode
Version: 0.1.12
Summary: Cross platform framework for splitting and parallel encoding of video
Home-page: https://github.com/parallelencode/PyParallelEncode
Author: Parallel Encoders
Author-email: eli.stonium@gmail.com
License: UNKNOWN
Platform: UNKNOWN
Classifier: Programming Language :: Python :: 3
Classifier: License :: OSI Approved :: GNU General Public License v3 or later (GPLv3+)
Classifier: Operating System :: OS Independent
Requires-Python: >=3.6
Requires-Dist: numpy
Requires-Dist: psutil
Requires-Dist: scipy
Provides-Extra: lsmash_splitting
Requires-Dist: vapoursynth ; extra == 'lsmash_splitting'
Provides-Extra: pyscenedetect_scene_detection
Requires-Dist: opencv-python ; extra == 'pyscenedetect_scene_detection'
Requires-Dist: scenedetect[opencv] ; extra == 'pyscenedetect_scene_detection'
